{
  "kind": "collectionType",
  "collectionName": "glossaires",
  "info": {
    "singularName": "glossaire",
    "pluralName": "glossaires",
    "displayName": "Glossaire"
  },
  "options": {
    "draftAndPublish": true
  },
  "pluginOptions": {
    "i18n": {
      "localized": true
    }
  },
  "attributes": {
    "nom": {
      "type": "string",
      "pluginOptions": {
        "i18n": {
          "localized": true
        }
      }
    },
    "definition": {
      "type": "blocks",
      "pluginOptions": {
        "i18n": {
          "localized": true
        }
      }
    },
    "image": {
      "type": "media",
      "pluginOptions": {
        "i18n": {
          "localized": true
        }
      },
      "multiple": false,
      "allowedTypes": [
        "images",
        "files",
        "videos",
        "audios"
      ]
    }
  }
}
